iso4217/__init__.py
iso4217/__init__.pyi
iso4217/py.typed
iso4217/table.xml
iso4217/test.py
iso4217-1.15.20260101.dist-info/METADATA
iso4217-1.15.20260101.dist-info/WHEEL
iso4217-1.15.20260101.dist-info/top_level.txt
iso4217-1.15.20260101.dist-info/RECORD
