Metadata-Version: 2.4
Name: iso4217
Version: 1.15.20260101
Summary: ISO 4217 currency data package for Python
Home-page: https://github.com/dahlia/iso4217
Author: Hong Minhee
Author-email: hong.minhee@gmail.com
License: Public Domain
Keywords: internationalization i18n currency iso4217
Platform: any
Classifier: Development Status :: 5 - Production/Stable
Classifier: Intended Audience :: Developers
Classifier: License :: Public Domain
Classifier: Operating System :: OS Independent
Classifier: Programming Language :: Python :: 3.6
Classifier: Programming Language :: Python :: 3.7
Classifier: Programming Language :: Python :: 3.8
Classifier: Programming Language :: Python :: 3.9
Classifier: Programming Language :: Python :: 3.10
Classifier: Programming Language :: Python :: 3.11
Classifier: Programming Language :: Python :: 3.12
Classifier: Programming Language :: Python :: 3.13
Classifier: Programming Language :: Python :: 3.14
Classifier: Programming Language :: Python :: Implementation :: CPython
Classifier: Programming Language :: Python :: Implementation :: PyPy
Classifier: Programming Language :: Python :: Implementation :: Stackless
Classifier: Topic :: Office/Business :: Financial
Classifier: Topic :: Software Development :: Internationalization
Requires-Python: >=3.6
Requires-Dist: importlib-resources; python_version > "3.5" and python_version < "3.9"
